aiotube/__init__.py
aiotube/channel.py
aiotube/errors.py
aiotube/extras.py
aiotube/https.py
aiotube/patterns.py
aiotube/playlist.py
aiotube/pool.py
aiotube/query.py
aiotube/stream.py
aiotube/utils.py
aiotube/video.py
aiotube-1.7.2.dist-info/LICENSE
aiotube-1.7.2.dist-info/METADATA
aiotube-1.7.2.dist-info/WHEEL
aiotube-1.7.2.dist-info/top_level.txt
aiotube-1.7.2.dist-info/RECORD
