Metadata-Version: 2.1
Name: aiotube
Version: 1.7.2
Summary: Access YouTube Public Data without YouTube API
Home-page: https://github.com/jnsougata/aiotube
Author: jnsougata
Author-email: jnsougata@gmail.com
Project-URL: Documentation, https://aiotube.readthedocs.io/en/latest/
Project-URL: Source, https://github.com/jnsougata/aiotube
Keywords: youtube,youtube-data,youtube-api,youtube-data-api-v3
Classifier: License :: OSI Approved :: MIT License
Classifier: Intended Audience :: Developers
Classifier: Natural Language :: English
Classifier: Operating System :: OS Independent
Classifier: Programming Language :: Python :: 3.8
Classifier: Programming Language :: Python :: 3.9
Classifier: Programming Language :: Python :: 3.10
Classifier: Topic :: Internet
Classifier: Topic :: Software Development :: Libraries
Classifier: Topic :: Software Development :: Libraries :: Python Modules
Classifier: Topic :: Utilities
Requires-Python: >=3.8.0
License-File: LICENSE
Requires-Dist: urllib3
